pyvim/__init__.py
pyvim/__main__.py
pyvim/completion.py
pyvim/editor.py
pyvim/editor_buffer.py
pyvim/enums.py
pyvim/help.py
pyvim/key_bindings.py
pyvim/layout.py
pyvim/lexer.py
pyvim/rc_file.py
pyvim/reporting.py
pyvim/style.py
pyvim/welcome_message.py
pyvim/window_arrangement.py
pyvim/commands/__init__.py
pyvim/commands/commands.py
pyvim/commands/completer.py
pyvim/commands/grammar.py
pyvim/commands/handler.py
pyvim/commands/lexer.py
pyvim/commands/preview.py
pyvim/entry_points/__init__.py
pyvim/entry_points/run_pyvim.py
pyvim/io/__init__.py
pyvim/io/backends.py
pyvim/io/base.py
pyvim-3.0.3.dist-info/LICENSE
pyvim-3.0.3.dist-info/METADATA
pyvim-3.0.3.dist-info/WHEEL
pyvim-3.0.3.dist-info/entry_points.txt
pyvim-3.0.3.dist-info/top_level.txt
pyvim-3.0.3.dist-info/RECORD
