Metadata-Version: 2.1
Name: pyvim
Version: 3.0.3
Summary: Pure Python Vi Implementation
Home-page: https://github.com/jonathanslenders/pyvim
Author: Jonathan Slenders
License: BSD License
Platform: UNKNOWN
License-File: LICENSE
